{
  "$schema": "https://biomejs.dev/schemas/2.0.6/schema.json",
  "vcs": { "enabled": false, "clientKind": "git", "useIgnoreFile": false },
  "files": { "ignoreUnknown": false },
  "formatter": {
    "enabled": true,
    "formatWithErrors": false,
    "indentStyle": "space",
    "indentWidth": 2,
    "lineEnding": "lf",
    "lineWidth": 80,
    "attributePosition": "auto",
    "bracketSameLine": false,
    "bracketSpacing": true,
    "expand": "auto",
    "useEditorconfig": true
  },
  "linter": {
    "enabled": true,
    "rules": {
      "recommended": false,
      "complexity": {
        "noBannedTypes": "error",
        "noUselessTypeConstraint": "error"
      },
      "correctness": {
        "noPrecisionLoss": "error",
        "noUnusedVariables": "error"
      },
      "style": {
        "noNamespace": "error",
        "useArrayLiterals": "error",
        "useAsConstAssertion": "error",
        "useBlockStatements": "off"
      },
      "suspicious": {
        "noExplicitAny": "off",
        "noExtraNonNullAssertion": "error",
        "noMisleadingInstantiator": "error",
        "noUnsafeDeclarationMerging": "error"
      }
    },
    "includes": ["**", "**/.eslintrc.js"]
  },
  "javascript": {
    "formatter": {
      "jsxQuoteStyle": "double",
      "quoteProperties": "asNeeded",
      "trailingCommas": "all",
      "semicolons": "asNeeded",
      "arrowParentheses": "always",
      "bracketSameLine": false,
      "quoteStyle": "single",
      "attributePosition": "auto",
      "bracketSpacing": true
    }
  },
  "html": { "formatter": { "selfCloseVoidElements": "always" } },
  "overrides": [
    {
      "includes": ["*.ts", "*.tsx", "*.mts", "*.cts"],
      "linter": {
        "rules": {
          "complexity": { "noArguments": "error" },
          "correctness": {
            "noConstAssign": "off",
            "noGlobalObjectCalls": "off",
            "noInvalidConstructorSuper": "off",
            "noSetterReturn": "off",
            "noUndeclaredVariables": "off",
            "noUnreachable": "off",
            "noUnreachableSuper": "off"
          },
          "style": { "useConst": "error" },
          "suspicious": {
            "noDuplicateClassMembers": "off",
            "noDuplicateObjectKeys": "off",
            "noDuplicateParameters": "off",
            "noFunctionAssign": "off",
            "noImportAssign": "off",
            "noRedeclare": "off",
            "noUnsafeNegation": "off",
            "noVar": "error",
            "useGetterReturn": "off"
          }
        }
      }
    }
  ],
  "assist": {
    "enabled": true,
    "actions": { "source": { "organizeImports": "on" } }
  }
}
